vesselviz/__init__.py
vesselviz/animator.py
vesselviz/utils.py
vesselviz-0.1.0.dist-info/licenses/LICENSE
vesselviz-0.1.0.dist-info/METADATA
vesselviz-0.1.0.dist-info/WHEEL
vesselviz-0.1.0.dist-info/top_level.txt
vesselviz-0.1.0.dist-info/RECORD
